pioreactor_custom_dosing_automation/__init__.py
pioreactor_custom_dosing_automation/additional_config.ini
pioreactor_custom_dosing_automation/ui/contrib/automations/dosing/my_custom_dosing_automation.yaml
pioreactor_custom_dosing_automation-0.0.1.dist-info/LICENSE
pioreactor_custom_dosing_automation-0.0.1.dist-info/METADATA
pioreactor_custom_dosing_automation-0.0.1.dist-info/WHEEL
pioreactor_custom_dosing_automation-0.0.1.dist-info/entry_points.txt
pioreactor_custom_dosing_automation-0.0.1.dist-info/top_level.txt
pioreactor_custom_dosing_automation-0.0.1.dist-info/RECORD
