Metadata-Version: 2.1
Name: pioreactor-custom-dosing-automation
Version: 0.0.1
Summary: Example dosing automation plugin
Home-page: https://github.com/Pioreactor/pioreactor-custom-dosing-automation
Author-email: cam@pioreactor.com
License: MIT
Platform: UNKNOWN
License-File: LICENSE
